bdjobs_scraper/__init__.py
bdjobs_scraper/clean_html.py
bdjobs_scraper/parse_id.py
bdjobs_scraper/request_details.py
bdjobs_scraper/scraper.py
bdjobs_scraper-0.1.3.dist-info/LICENSE
bdjobs_scraper-0.1.3.dist-info/METADATA
bdjobs_scraper-0.1.3.dist-info/WHEEL
bdjobs_scraper-0.1.3.dist-info/RECORD
